grosnap/__init__.py
grosnap/script.py
grosnap-0.0.13.dist-info/METADATA
grosnap-0.0.13.dist-info/WHEEL
grosnap-0.0.13.dist-info/entry_points.txt
grosnap-0.0.13.dist-info/license_files/LICENSE
grosnap-0.0.13.dist-info/RECORD
