Metadata-Version: 2.1
Name: grosnap
Version: 0.0.13
Summary: Python package manager grosnap
Project-URL: Repository, https://github.com/gro-intelligence/gro-internal/tree/main/experimental/grosnap_package
Author-email: Jacques Paye <jacques.paye@gro-intelligence.com>
Classifier: License :: OSI Approved :: MIT License
Classifier: Operating System :: OS Independent
Classifier: Programming Language :: Python :: 3
Requires-Python: >=3.7
Requires-Dist: packaging
Requires-Dist: requests
